src/__init__.py
src/__main__.py
src/hotel_data.py
src/http_server.py
src/server.py
src/sse_server.py
dida_mcp_server-1.0.2.dist-info/METADATA
dida_mcp_server-1.0.2.dist-info/WHEEL
dida_mcp_server-1.0.2.dist-info/entry_points.txt
dida_mcp_server-1.0.2.dist-info/top_level.txt
dida_mcp_server-1.0.2.dist-info/RECORD
